cutflow_compare/__init__.py
cutflow_compare/cutflow_compare.py
cutflow_compare-2.3.0.dist-info/licenses/LICENSE
cutflow_compare-2.3.0.dist-info/METADATA
cutflow_compare-2.3.0.dist-info/WHEEL
cutflow_compare-2.3.0.dist-info/entry_points.txt
cutflow_compare-2.3.0.dist-info/top_level.txt
cutflow_compare-2.3.0.dist-info/RECORD
