Metadata-Version: 2.4
Name: cutflow_compare
Version: 2.3.0
Summary: Compare cutflow (and countflow) histograms from ROOT files, with region name mapping and diagnostics.
Home-page: https://github.com/ibeuler/cutflow_compare
Author: Ibrahim H.I. ABUSHAWISH
Author-email: "Ibrahim H.I. ABUSHAWISH" <ibrahim.hamed2701@gmail.com>
License: MIT License
Project-URL: Homepage, https://github.com/ibeuler/cutflow_compare
Project-URL: Repository, https://github.com/ibeuler/cutflow_compare
Project-URL: Documentation, https://github.com/ibeuler/cutflow_compare#readme
Project-URL: Issues, https://github.com/ibeuler/cutflow_compare/issues
Keywords: ROOT,cutflow,histograms,data analysis,CutLang
Classifier: Development Status :: 5 - Production/Stable
Classifier: Intended Audience :: Science/Research
Classifier: Topic :: Scientific/Engineering :: Physics
Classifier: Programming Language :: Python :: 3
Classifier: Programming Language :: Python :: 3.6
Classifier: Programming Language :: Python :: 3.7
Classifier: Programming Language :: Python :: 3.8
Classifier: Programming Language :: Python :: 3.9
Classifier: Programming Language :: Python :: 3.10
Classifier: License :: OSI Approved :: MIT License
Classifier: Operating System :: OS Independent
Requires-Python: >=3.6
License-File: LICENSE
Requires-Dist: pandas>=1.0
Requires-Dist: uncertainties>=3.2.3
Requires-Dist: prettytable>=3.0.0
Dynamic: author
Dynamic: home-page
Dynamic: license-file
Dynamic: requires-python
